yandex_search_api/__init__.py
yandex_search_api/async_client.py
yandex_search_api/client.py
yandex_search_api/exceptions.py
yandex_search_api/regions.py
yandex_search_api-0.1.7.dist-info/METADATA
yandex_search_api-0.1.7.dist-info/WHEEL
yandex_search_api-0.1.7.dist-info/licenses/LICENSE
yandex_search_api-0.1.7.dist-info/RECORD
